pinjected_rate_limit/__init__.py
pinjected_rate_limit/rate_limitter.py
pinjected_rate_limit-0.1.0.dist-info/METADATA
pinjected_rate_limit-0.1.0.dist-info/WHEEL
pinjected_rate_limit-0.1.0.dist-info/RECORD
