Metadata-Version: 2.3
Name: pinjected-rate-limit
Version: 0.1.0
Summary: Add your description here
Author-email: proboscis <nameissoap@gmail.com>
Requires-Python: >=3.8
Requires-Dist: pinjected>=0.2.203
